{
  "main": {
    "id": "ef004bada6e56b2a",
    "type": "split",
    "children": [
      {
        "id": "1688025e1e06174c",
        "type": "tabs",
        "children": [
          {
            "id": "232eae61798278c6",
            "type": "leaf",
            "state": {
              "type": "markdown",
              "state": {
                "file": "CS186/Lecture 10 - Joins.md",
                "mode": "source",
                "source": false
              },
              "icon": "lucide-file",
              "title": "Lecture 10 - Joins"
            }
          },
          {
            "id": "89a3c2e397cf1538",
            "type": "leaf",
            "state": {
              "type": "markdown",
              "state": {
                "file": "Math 53/Derivative Rules.md",
                "mode": "source",
                "source": false
              },
              "icon": "lucide-file",
              "title": "Derivative Rules"
            }
          },
          {
            "id": "70765804f423987a",
            "type": "leaf",
            "state": {
              "type": "image",
              "state": {
                "file": "CS186/img/Pasted image 20250326101801.png"
              },
              "icon": "lucide-image",
              "title": "Pasted image 20250326101801"
            }
          },
          {
            "id": "8f4f9e464bd4a630",
            "type": "leaf",
            "state": {
              "type": "markdown",
              "state": {
                "file": "Math 53/15.2 - Double Integrals.md",
                "mode": "source",
                "source": false
              },
              "icon": "lucide-file",
              "title": "15.2 - Double Integrals"
            }
          },
          {
            "id": "970cc81fdcc11e91",
            "type": "leaf",
            "state": {
              "type": "markdown",
              "state": {
                "file": "Math 53/14.6 Directional Derivatives and Gradient Vector.md",
                "mode": "source",
                "source": false
              },
              "icon": "lucide-file",
              "title": "14.6 Directional Derivatives and Gradient Vector"
            }
          },
          {
            "id": "d8cc6bb97c4d59b5",
            "type": "leaf",
            "state": {
              "type": "markdown",
              "state": {
                "file": "Math 53/Multivariable Calculus.md",
                "mode": "source",
                "source": false
              },
              "icon": "lucide-file",
              "title": "Multivariable Calculus"
            }
          },
          {
            "id": "5ab0236fbb3017db",
            "type": "leaf",
            "state": {
              "type": "markdown",
              "state": {
                "file": "Math 53/Multivariable Calculus.md",
                "mode": "source",
                "source": false
              },
              "icon": "lucide-file",
              "title": "Multivariable Calculus"
            }
          },
          {
            "id": "f177f20efbe45cd5",
            "type": "leaf",
            "state": {
              "type": "markdown",
              "state": {
                "file": "Math 53/14.2 Limits and Continuity.md",
                "mode": "source",
                "source": false
              },
              "icon": "lucide-file",
              "title": "14.2 Limits and Continuity"
            }
          },
          {
            "id": "df03afb1cd100ce5",
            "type": "leaf",
            "state": {
              "type": "markdown",
              "state": {
                "file": "Math 53/Multivariable Calculus.md",
                "mode": "source",
                "source": false
              },
              "icon": "lucide-file",
              "title": "Multivariable Calculus"
            }
          },
          {
            "id": "245282ba639dabff",
            "type": "leaf",
            "state": {
              "type": "markdown",
              "state": {
                "file": "Math 53/13.2 Derivatives and Integrals of Vector Functions.md",
                "mode": "source",
                "source": false
              },
              "icon": "lucide-file",
              "title": "13.2 Derivatives and Integrals of Vector Functions"
            }
          },
          {
            "id": "055831a4a52e033c",
            "type": "leaf",
            "state": {
              "type": "markdown",
              "state": {
                "file": "CS186/Lecture 3 - Disk, files, and buffers.md",
                "mode": "source",
                "source": false
              },
              "icon": "lucide-file",
              "title": "Lecture 3 - Disk, files, and buffers"
            }
          },
          {
            "id": "f2f5dc0603e427b2",
            "type": "leaf",
            "state": {
              "type": "markdown",
              "state": {
                "file": "Math 53/Multivariable Calculus.md",
                "mode": "source",
                "source": false
              },
              "icon": "lucide-file",
              "title": "Multivariable Calculus"
            }
          }
        ],
        "currentTab": 11
      }
    ],
    "direction": "vertical"
  },
  "left": {
    "id": "f84065c138168b9d",
    "type": "split",
    "children": [
      {
        "id": "61c652ef6dced7b3",
        "type": "tabs",
        "children": [
          {
            "id": "1a93259cabede32e",
            "type": "leaf",
            "state": {
              "type": "file-explorer",
              "state": {
                "sortOrder": "alphabetical",
                "autoReveal": false
              },
              "icon": "lucide-folder-closed",
              "title": "Files"
            }
          },
          {
            "id": "7c21d35d826c7922",
            "type": "leaf",
            "state": {
              "type": "search",
              "state": {
                "query": "tag:#Lecture6",
                "matchingCase": false,
                "explainSearch": false,
                "collapseAll": false,
                "extraContext": false,
                "sortOrder": "alphabetical"
              },
              "icon": "lucide-search",
              "title": "Search"
            }
          },
          {
            "id": "a30e7e1573eb3a61",
            "type": "leaf",
            "state": {
              "type": "starred",
              "state": {},
              "icon": "lucide-file",
              "title": "Plugin no longer active"
            }
          },
          {
            "id": "a8a09377ab0af489",
            "type": "leaf",
            "state": {
              "type": "bookmarks",
              "state": {},
              "icon": "lucide-bookmark",
              "title": "Bookmarks"
            }
          }
        ]
      }
    ],
    "direction": "horizontal",
    "width": 200
  },
  "right": {
    "id": "620b7056f36830f6",
    "type": "split",
    "children": [
      {
        "id": "9e849edd57f3fecb",
        "type": "tabs",
        "children": [
          {
            "id": "2a1900dc699d1c59",
            "type": "leaf",
            "state": {
              "type": "backlink",
              "state": {
                "file": "CS186/Lecture 8 - Buffer Management.md",
                "collapseAll": false,
                "extraContext": false,
                "sortOrder": "alphabetical",
                "showSearch": false,
                "searchQuery": "",
                "backlinkCollapsed": false,
                "unlinkedCollapsed": true
              },
              "icon": "links-coming-in",
              "title": "Backlinks for Lecture 8 - Buffer Management"
            }
          },
          {
            "id": "d6b4eb4cb50d4642",
            "type": "leaf",
            "state": {
              "type": "outgoing-link",
              "state": {
                "file": "CS186/Textbook Notes.md",
                "linksCollapsed": false,
                "unlinkedCollapsed": true
              },
              "icon": "links-going-out",
              "title": "Outgoing links from Textbook Notes"
            }
          },
          {
            "id": "e6fc91351bd7c1d9",
            "type": "leaf",
            "state": {
              "type": "tag",
              "state": {
                "sortOrder": "frequency",
                "useHierarchy": true
              },
              "icon": "lucide-tags",
              "title": "Tags"
            }
          },
          {
            "id": "216bb5209496cfc9",
            "type": "leaf",
            "state": {
              "type": "outline",
              "state": {
                "file": "CS186/Textbook Notes.md"
              },
              "icon": "lucide-list",
              "title": "Outline of Textbook Notes"
            }
          },
          {
            "id": "f1b6adb52106db53",
            "type": "leaf",
            "state": {
              "type": "all-properties",
              "state": {
                "sortOrder": "frequency",
                "showSearch": false,
                "searchQuery": ""
              },
              "icon": "lucide-archive",
              "title": "All properties"
            }
          }
        ]
      }
    ],
    "direction": "horizontal",
    "width": 200,
    "collapsed": true
  },
  "left-ribbon": {
    "hiddenItems": {
      "obsidian-excalidraw-plugin:New drawing": false,
      "switcher:Open quick switcher": false,
      "graph:Open graph view": false,
      "canvas:Create new canvas": false,
      "daily-notes:Open today's daily note": false,
      "templates:Insert template": false,
      "command-palette:Open command palette": false
    }
  },
  "active": "f2f5dc0603e427b2",
  "lastOpenFiles": [
    "Math 53/Derivative Rules.md",
    "Math 53/Multivariable Calculus.md",
    "Math 53/14.8 Lagrange Multipliers.md",
    "CS186/Lecture 3 - Disk, files, and buffers.md",
    "Math 53/14.4 Tangent Planes and Linear Approximations.md",
    "Math 53/14.2 Limits and Continuity.md",
    "CS186/Lecture 11 - Iterators and Relational Algebra.md",
    "Math 53/13.1 Vector Functions and Space Curves.md",
    "Math 53/13.2 Derivatives and Integrals of Vector Functions.md",
    "Math 53/14.1 Functions of Several Variables.md",
    "Math 53/14.3 Partial Derivatives.md",
    "Math 53/14.6 Directional Derivatives and Gradient Vector.md",
    "CS186/img/Pasted image 20250401180220.png",
    "CS186/img/Pasted image 20250401173444.png",
    "CS186/img/Pasted image 20250401172336.png",
    "Math 53/img/Pasted image 20250401185349.png",
    "CS186/Lecture 16 - Recovery I.md",
    "Math 53/15.5 Surface Area.md",
    "Math 53/15.2 - Double Integrals.md",
    "Math 53/img/Unit-circle.png",
    "CS186/img/Pasted image 20250326101801.png",
    "Math 53/14.7 Maximum and Minimum Values.md",
    "CS186/Lecture 10 - Joins.md",
    "CS170/Lecture 3 - Selection and Recurrence Relation.md",
    "CS186/Lecture 8 - Buffer Management.md",
    "CS170/CS170 - Efficient Algorithms.md",
    "CS186/CS186 - Intro to Database Systems.md",
    "React/React Basics.md",
    "CS186/img/Pasted image 20250325120005.png",
    "CS186/Lecture 9 - Sorting and Hashing.md",
    "CS186/img/Pasted image 20250325121936.png",
    "CS186/img/Pasted image 20250325113657.png",
    "CS186/img/Pasted image 20250325114744.png",
    "CS70/Discrete Math.md",
    "CS170/Lecture 15 - Linear Programming.md",
    "CS170/Lecture 13 - Dynamic Programming III.md",
    "Plugins/Ink/Writing/2025.3.5 - 21.26pm.writing",
    "Plugins/Ink/Writing/2025.3.5 - 21.22pm.writing",
    "Plugins/Ink/Drawing/2025.3.6 - 15.11pm.drawing",
    "Plugins/Ink/Drawing/2025.3.6 - 14.52pm.drawing",
    "Plugins/Ink/Drawing/2025.3.5 - 21.46pm.drawing",
    "Plugins/Ink/Drawing/2025.3.5 - 21.33pm.drawing",
    "Plugins/Ink/Drawing/2025.3.5 - 21.32pm.drawing",
    "Plugins/Ink/Drawing/2025.3.5 - 21.28pm.drawing",
    "Plugins/Ink/Drawing/2025.3.5 - 21.24pm.drawing",
    "Plugins/Ink/Drawing/2025.3.5 - 21.22pm.drawing",
    "Untitled.canvas"
  ]
}